LICENSE
MANIFEST.in
README.md
requirements-style.txt
requirements-test.txt
requirements.txt
setup.cfg
setup.py
docker_registry/__init__.py
docker_registry/core/__init__.py
docker_registry/core/boto.py
docker_registry/core/compat.py
docker_registry/core/driver.py
docker_registry/core/exceptions.py
docker_registry/core/lru.py
docker_registry/drivers/__init__.py
docker_registry/drivers/dumb.py
docker_registry/drivers/file.py
docker_registry/testing/__init__.py
docker_registry/testing/driver.py
docker_registry/testing/mock_boto.py
docker_registry/testing/mock_dict.py
docker_registry/testing/query.py
docker_registry/testing/utils.py
docker_registry_core.egg-info/PKG-INFO
docker_registry_core.egg-info/SOURCES.txt
docker_registry_core.egg-info/dependency_links.txt
docker_registry_core.egg-info/namespace_packages.txt
docker_registry_core.egg-info/requires.txt
docker_registry_core.egg-info/top_level.txt
docker_registry_core.egg-info/zip-safe