Metadata-Version: 1.1
Name: docker-registry-core
Version: 1.0.6
Summary: Docker registry core package
Home-page: https://github.com/dotcloud/docker-registry
Author: Docker
Author-email: dev@docker.com
License: 
